chronflow/__init__.py
chronflow/config.py
chronflow/daemon.py
chronflow/decorators.py
chronflow/discovery.py
chronflow/logging.py
chronflow/metrics.py
chronflow/py.typed
chronflow/retry.py
chronflow/scheduler.py
chronflow/task.py
chronflow/backends/__init__.py
chronflow/backends/base.py
chronflow/backends/memory.py
chronflow/backends/rabbitmq_backend.py
chronflow/backends/redis_backend.py
chronflow/backends/sqlite_backend.py
chronflow-0.3.0.dist-info/METADATA
chronflow-0.3.0.dist-info/WHEEL
chronflow-0.3.0.dist-info/licenses/LICENSE
chronflow-0.3.0.dist-info/RECORD
