Metadata-Version: 2.4
Name: chronflow
Version: 0.3.0
Summary: A high-performance async task scheduler with cron support, auto-discovery, retry mechanism, and configuration management
Project-URL: Homepage, https://github.com/getaix/chronflow
Project-URL: Documentation, https://getaix.github.io/chronflow
Project-URL: Repository, https://github.com/getaix/chronflow
Project-URL: Issues, https://github.com/getaix/chronflow/issues
Project-URL: Changelog, https://getaix.github.io/chronflow/changelog/
Author-email: getaix <develop@getaix.tech>
License: MIT
License-File: LICENSE
Keywords: async,asyncio,cron,queue,scheduler,task,timer
Classifier: Development Status :: 4 - Beta
Classifier: Framework :: AsyncIO
Classifier: Intended Audience :: Developers
Classifier: License :: OSI Approved :: MIT License
Classifier: Programming Language :: Python :: 3
Classifier: Programming Language :: Python :: 3.11
Classifier: Programming Language :: Python :: 3.12
Classifier: Programming Language :: Python :: 3.13
Classifier: Topic :: Software Development :: Libraries :: Python Modules
Classifier: Topic :: System :: Monitoring
Classifier: Typing :: Typed
Requires-Python: >=3.11
Requires-Dist: croniter>=2.0.0
Requires-Dist: pydantic-settings>=2.0.0
Requires-Dist: pydantic>=2.0.0
Requires-Dist: python-dateutil>=2.8.0
Requires-Dist: tenacity>=8.2.0
Provides-Extra: all
Requires-Dist: aio-pika>=9.0.0; extra == 'all'
Requires-Dist: loguru>=0.7.0; extra == 'all'
Requires-Dist: pyyaml>=6.0; extra == 'all'
Requires-Dist: redis[hiredis]>=5.0.0; extra == 'all'
Requires-Dist: structlog>=23.0.0; extra == 'all'
Provides-Extra: dev
Requires-Dist: black>=23.0.0; extra == 'dev'
Requires-Dist: build>=1.0.0; extra == 'dev'
Requires-Dist: mypy>=1.5.0; extra == 'dev'
Requires-Dist: pytest-asyncio>=0.21.0; extra == 'dev'
Requires-Dist: pytest-cov>=4.1.0; extra == 'dev'
Requires-Dist: pytest>=7.4.0; extra == 'dev'
Requires-Dist: ruff>=0.1.0; extra == 'dev'
Requires-Dist: twine>=4.0.0; extra == 'dev'
Provides-Extra: docs
Requires-Dist: mkdocs-material>=9.5.0; extra == 'docs'
Requires-Dist: mkdocs>=1.5.0; extra == 'docs'
Requires-Dist: mkdocstrings[python]>=0.24.0; extra == 'docs'
Requires-Dist: pymdown-extensions>=10.7.0; extra == 'docs'
Provides-Extra: loguru
Requires-Dist: loguru>=0.7.0; extra == 'loguru'
Provides-Extra: rabbitmq
Requires-Dist: aio-pika>=9.0.0; extra == 'rabbitmq'
Provides-Extra: redis
Requires-Dist: redis[hiredis]>=5.0.0; extra == 'redis'
Provides-Extra: structlog
Requires-Dist: structlog>=23.0.0; extra == 'structlog'
Provides-Extra: yaml
Requires-Dist: pyyaml>=6.0; extra == 'yaml'
